CHANGELOG.txt
LICENSE.txt
MANIFEST.in
README.txt
ez_setup.py
setup.cfg
setup.py
DatabasePipe.egg-info/PKG-INFO
DatabasePipe.egg-info/SOURCES.txt
DatabasePipe.egg-info/dependency_links.txt
DatabasePipe.egg-info/entry_points.txt
DatabasePipe.egg-info/not-zip-safe
DatabasePipe.egg-info/requires.txt
DatabasePipe.egg-info/top_level.txt
databasepipe/__init__.py
databasepipe/setup.py
databasepipe/helper/__init__.py
databasepipe/helper/connection.py
databasepipe/helper/plugin.py
databasepipe/service/__init__.py
databasepipe/service/connection.py
doc/Makefile
doc/index.txt
doc/source/api.rst
doc/source/conf.py
doc/source/index.rst
doc/source/manual.rst
example/README.txt
test/README.txt
test/doc.py
test/sqlite.conf
test/unit.py