Metadata-Version: 1.0
Name: DatabasePipe
Version: 2.2.1
Summary: A pipe to connect various SQL databases to a PipeStack application. Supports PostgreSQL, SQLite and SQLServer 2000 via plugins.
Home-page: http://jimmyg.org/work/code/databasepipe/index.html
Author: James Gardner
Author-email: james@<package hompage domain>
License: GNU AGPLv3
Platform: UNKNOWN
Classifier: Development Status :: 3 - Alpha
Classifier: License :: OSI Approved :: GNU Affero General Public License v3
Classifier: Programming Language :: Python
